[
	{
		"Incident": "INC0013294 ",
		"Origen": "ADO-023",
		"SERVICIO SOLICITADO": "CORREO - FALLA",
		"CODIGO": 13490301,
		"TORRE QUE ATIENDE": "I-MX-ADO-CSC-SDK-SERVICE DESK",
		"PALABRAS OBLIGATORIAS QUE DEBE CONTENER EL CORREO": "365",
		"PALABRAS DE LAS CUALES AL MENOS UNA DEBE CONTENER EL CORREO": "CAMBIO, MODIFICACION, CAMBIAR, QUITAR, AGREGAR",
		"REQUIERE ADJUNTOS": "NO",
		"SE GENERA IN ?": "SI",
		"Condicion (Cuando no existe ninguna palabra clave se asigna a service desk)": "N\/A"
	}
]